mvnx/__init__.py
mvnx/models.py
mvnx/mvnx.py
mvnx-0.2.dist-info/LICENSE
mvnx-0.2.dist-info/METADATA
mvnx-0.2.dist-info/WHEEL
mvnx-0.2.dist-info/entry_points.txt
mvnx-0.2.dist-info/top_level.txt
mvnx-0.2.dist-info/RECORD
