Metadata-Version: 2.1
Name: mvnx
Version: 0.2
Summary: A lightweight commandline parser for the MVNX motion capture file format
Home-page: https://github.com/alexharston/mvnx
Author: Alex Harston
Author-email: alex@harston.io
License: MIT
Platform: UNKNOWN
Classifier: Programming Language :: Python :: 3
Classifier: License :: OSI Approved :: MIT License
Classifier: Operating System :: OS Independent
Requires-Python: >=3.6
License-File: LICENSE
Requires-Dist: numpy
Requires-Dist: argparse
